./.gitignore
./LICENSE.txt
./README.md
./micro_liquid.py
./py.typed
./pyproject.toml
./.github/FUNDING.yml
./.github/workflows/lint.yaml
./.github/workflows/tests.yaml
./.github/workflows/typing.yaml
./tests/__init__.py
./tests/test_compound_expressions.py
./tests/test_custom_serializer.py
./tests/test_for_tag.py
./tests/test_if_tag.py
./tests/test_output.py
./tests/test_strict_undefined.py
./tests/test_syntax_errors.py
./tests/test_unescape.py
./tests/test_whitespace_control.py
micro_liquid-0.1.0.dist-info/METADATA
micro_liquid-0.1.0.dist-info/WHEEL
micro_liquid-0.1.0.dist-info/licenses/LICENSE.txt
micro_liquid-0.1.0.dist-info/RECORD
