Metadata-Version: 2.4
Name: micro-liquid
Version: 0.1.0
Summary: Minimal Liquid-like templating
Project-URL: Documentation, https://github.com/jg-rp/micro-liquid#readme
Project-URL: Issues, https://github.com/jg-rp/micro-liquid/issues
Project-URL: Source, https://github.com/jg-rp/micro-liquid
Author-email: James Prior <jamesgr.prior@gmail.com>
License-Expression: MIT
License-File: LICENSE.txt
Classifier: Development Status :: 4 - Beta
Classifier: License :: OSI Approved :: MIT License
Classifier: Programming Language :: Python
Classifier: Programming Language :: Python :: 3.10
Classifier: Programming Language :: Python :: 3.11
Classifier: Programming Language :: Python :: 3.12
Classifier: Programming Language :: Python :: 3.13
Classifier: Programming Language :: Python :: Implementation :: CPython
Classifier: Programming Language :: Python :: Implementation :: PyPy
Requires-Python: >=3.10
